[
    {
        "id": "a20c5589-6dbd-40af-91ad-05ddfe26643b",
        "text": "Don't talk about what you have done or what you are going to do.",
        "author": "Thomas Jefferson",
        "votes": [],
        "score": 0,
        "date": 1690982835126
    },
    {
        "id": "613372ff-2686-4ba0-93ac-625b85b16ba0",
        "text": "Getting lost along your path is a part of finding the path you are meant to be on.",
        "author": "Robin Sharma",
        "votes": [],
        "score": 0,
        "date": 1690982828279
    },
    {
        "id": "d1c01c52-f5cc-4c94-9810-625ff66934bd",
        "text": "Youth has no age.",
        "author": "Pablo Picasso",
        "votes": [],
        "score": 0,
        "date": 1690982821389
    },
    {
        "id": "9b848c35-69a7-4095-9146-3a882ee8b287",
        "text": "The moment you stop to think about whether you love someone, you've already stopped loving that person forever.",
        "author": "Carlos Ruiz Zafon",
        "votes": [],
        "score": 0,
        "date": 1690982814526
    },
    {
        "id": "124956a1-78e1-4868-a757-d8be6a930a78",
        "text": "Abundance of knowledge does not teach men to be wise.",
        "author": "Heraclitus",
        "votes": [],
        "score": 0,
        "date": 1690982598690
    },
    {
        "id": "9d44970a-b7ae-4df0-8795-1ce146544464",
        "text": "Some people feel the rain. Others just get wet. ",
        "author": "Bob Dylan",
        "votes": [],
        "score": 0,
        "date": 1690982591889
    },
    {
        "id": "319876dc-e629-47e5-9e09-ea2988f01573",
        "text": "The biggest adventure you can ever take is to live the life of your dreams. ",
        "author": "Oprah Winfrey",
        "votes": [],
        "score": 0,
        "date": 1690982585090
    },
    {
        "id": "4201dc39-12d7-497a-ba61-62e3f02b43f0",
        "text": "The older you get, the better you get. Unless you're a banana.",
        "author": "Betty White",
        "votes": [],
        "score": 0,
        "date": 1690982578255
    },
    {
        "id": "008e2ab1-7cc8-4288-8032-86dfc898dfed",
        "text": "Without the confidence, nothing can be accomplished.",
        "author": "Sathya Sai Baba",
        "votes": [],
        "score": 0,
        "date": 1690982571433
    }
]